MANIFEST.in
README.md
setup.py
djfront/__init__.py
djfront/__version__.py
djfront/cli.py
djfront/exceptions.py
djfront/help.py
djfront/models.py
djfront/status_codes.py
djfront/utils.py
djfront.egg-info/PKG-INFO
djfront.egg-info/SOURCES.txt
djfront.egg-info/dependency_links.txt
djfront.egg-info/entry_points.txt
djfront.egg-info/not-zip-safe
djfront.egg-info/requires.txt
djfront.egg-info/top_level.txt