Metadata-Version: 2.1
Name: djfront
Version: 0.1.1
Summary: Package Description:: Analysis the current django app and prepares all used static fiels for rendering.
Home-page: https://github.com/AzatAI/djfront
Author: Yaakov Azat
Author-email: yaakovazat@gmail.com
License: MIT
Project-URL: Source, https://github.com/AzatAI/djfront
Project-URL: Documentation, https://azat.ai
Platform: UNKNOWN
Classifier: Development Status :: 5 - Production/Stable
Classifier: Intended Audience :: Developers
Classifier: Natural Language :: English
Classifier: Programming Language :: Python
Classifier: Programming Language :: Python :: 3
Classifier: Programming Language :: Python :: 3.5
Classifier: Programming Language :: Python :: 3.6
Classifier: Programming Language :: Python :: 3.7
Classifier: Programming Language :: Python :: 3.8
Classifier: Programming Language :: Python :: Implementation :: CPython
Classifier: Programming Language :: Python :: Implementation :: PyPy
Requires-Python: >=3.5
